<?xml version="1.0" encoding="UTF-8"?>
<con:soapui-project id="1f6eb741-fc4e-473d-b479-2e53d78cf402" activeEnvironment="Default" name="rd_hw5" resourceRoot="" soapui-version="5.7.2" abortOnError="false" runType="SEQUENTIAL" xmlns:con="http://eviware.com/soapui/config"><con:settings><con:setting id="com.eviware.soapui.impl.wsdl.actions.iface.tools.soapui.TestRunnerAction@values-local"><![CDATA[<xml-fragment xmlns:con="http://eviware.com/soapui/config">
  <con:entry key="Report Format(s)" value=""/>
  <con:entry key="Host:Port" value=""/>
  <con:entry key="Export JUnit Results" value="false"/>
  <con:entry key="Export All" value="false"/>
  <con:entry key="Save After" value="false"/>
  <con:entry key="Add Settings" value="false"/>
  <con:entry key="WSS Password Type" value=""/>
  <con:entry key="TestSuite" value="CRUD test"/>
  <con:entry key="Endpoint" value=""/>
  <con:entry key="Select Report Type" value=""/>
  <con:entry key="System Properties" value=""/>
  <con:entry key="Password" value=""/>
  <con:entry key="Print Report" value="false"/>
  <con:entry key="Open Report" value="false"/>
  <con:entry key="Export JUnit Results with test properties" value="false"/>
  <con:entry key="Global Properties" value=""/>
  <con:entry key="Project Properties" value=""/>
  <con:entry key="Project Password" value=""/>
  <con:entry key="TestCase" value="&lt;all>"/>
  <con:entry key="Username" value=""/>
  <con:entry key="user-settings.xml Password" value=""/>
  <con:entry key="TestRunner Path" value=""/>
  <con:entry key="Environment" value="Default"/>
  <con:entry key="Coverage Report" value="false"/>
  <con:entry key="Enable UI" value="false"/>
  <con:entry key="Root Folder" value=""/>
  <con:entry key="Ignore Errors" value="false"/>
  <con:entry key="Domain" value=""/>
  <con:entry key="Tool Args" value=""/>
  <con:entry key="Save Project" value="false"/>
</xml-fragment>]]></con:setting></con:settings><con:interface xsi:type="con:RestService" id="0ffb3285-7266-462e-bc92-066420342591" wadlVersion="http://wadl.dev.java.net/2009/02" name="https://api.clickup.com" type="rest" xmlns:xsi="http://www.w3.org/2001/XMLSchema-instance"><con:settings/><con:definitionCache type="TEXT" rootPart=""/><con:endpoints><con:endpoint>https://app.clickup.com</con:endpoint></con:endpoints><con:resource name="" path="/api/v2/space/90121507775/tag" id="26afd658-e2cb-4373-b731-0216c1e1bd92"><con:settings/><con:parameters/><con:method name="GET_SPACE_TAGS" id="968d9fcb-06e1-4cf4-bfa7-beb275c965f0" method="GET"><con:settings/><con:parameters/><con:representation type="FAULT"><con:mediaType>application/json; charset=utf-8</con:mediaType><con:status>400</con:status><con:params/><con:element xmlns:tag="https://app.clickup.com/api/v2/space/90121507775/tag">tag:Fault</con:element></con:representation><con:representation type="RESPONSE"><con:mediaType>application/json; charset=utf-8</con:mediaType><con:status>200</con:status><con:params/><con:element xmlns:tag="https://app.clickup.com/api/v2/space/90121507775/tag">tag:Response</con:element></con:representation><con:representation type="RESPONSE"><con:mediaType>text/html; charset=utf-8</con:mediaType><con:status>200</con:status><con:params/><con:element>html</con:element></con:representation><con:request name="get space tags" id="ece4374c-4a11-41e1-b4cb-b367d7f4af83" mediaType="application/json"><con:settings><con:setting id="com.eviware.soapui.impl.wsdl.WsdlRequest@request-headers">&lt;entry key="Authorization" value="pk_2144423805_3GVK169890OTH81FLY3REPUZEXTG31S5" xmlns="http://eviware.com/soapui/config"/></con:setting></con:settings><con:endpoint>https://api.clickup.com</con:endpoint><con:request/><con:originalUri>https://app.clickup.com/api/v2/space/90121507775/tag</con:originalUri><con:credentials><con:authType>No Authorization</con:authType></con:credentials><con:jmsConfig JMSDeliveryMode="PERSISTENT"/><con:jmsPropertyConfig/><con:parameters/></con:request></con:method><con:method name="CREATE_SPACE_TAG" id="ec70cb16-41d3-4866-a2b7-a6755143870c" method="POST"><con:settings/><con:parameters/><con:representation type="REQUEST"><con:mediaType>application/json</con:mediaType><con:params/></con:representation><con:representation type="FAULT"><con:mediaType>application/json; charset=utf-8</con:mediaType><con:status>400</con:status><con:params/><con:element xmlns:tag="https://app.clickup.com/api/v2/space/90121507775/tag">tag:Fault</con:element></con:representation><con:representation type="RESPONSE"><con:mediaType>application/json; charset=utf-8</con:mediaType><con:status>200</con:status><con:params/><con:element>Response</con:element></con:representation><con:representation type="RESPONSE"><con:mediaType xsi:nil="true"/><con:status>0</con:status><con:params/><con:element>data</con:element></con:representation><con:request name="create space tag" id="a67613de-d7ae-4355-92c1-9f1bc1939f2b" mediaType="application/json" postQueryString="false"><con:settings><con:setting id="com.eviware.soapui.impl.wsdl.WsdlRequest@request-headers">&lt;entry key="Authorization" value="pk_2144423805_3GVK169890OTH81FLY3REPUZEXTG31S5" xmlns="http://eviware.com/soapui/config"/></con:setting></con:settings><con:endpoint>https://api.clickup.com</con:endpoint><con:request>{ 
  "tag": {
    "name": "${#Project#random_name}",
    "tag_fg": "#000000",
    "tag_bg": "#000000"
  }
}
</con:request><con:originalUri>https://app.clickup.com/api/v2/space/90121507775/tag</con:originalUri><con:credentials><con:selectedAuthProfile>No Authorization</con:selectedAuthProfile><con:authType>No Authorization</con:authType></con:credentials><con:jmsConfig JMSDeliveryMode="PERSISTENT"/><con:jmsPropertyConfig/><con:parameters/></con:request></con:method></con:resource><con:resource name="" path="/api/v2/space/90121507775/tag/${#Project#random_name}" id="26afd658-e2cb-4373-b731-0216c1e1bd92"><con:settings/><con:parameters/><con:method name="EDIT_SPACE_TAG" id="17c678f2-422b-4c55-b4f0-6aaf0f883f2e" method="PUT"><con:settings/><con:parameters/><con:representation type="REQUEST"><con:mediaType>application/json</con:mediaType><con:params/></con:representation><con:representation type="RESPONSE"><con:mediaType>text/html; charset=utf-8</con:mediaType><con:status>200</con:status><con:params/><con:element>html</con:element></con:representation><con:representation type="FAULT"><con:mediaType>application/json; charset=utf-8</con:mediaType><con:status>400</con:status><con:params/><con:element xmlns:app="https://app.clickup.com/">app:Fault</con:element></con:representation><con:representation type="RESPONSE"><con:mediaType>application/json; charset=utf-8</con:mediaType><con:status>200</con:status><con:params/><con:element>Response</con:element></con:representation><con:request name="edit space tag" id="514cd945-461d-4f7d-bc69-74aff4a9023b" mediaType="application/json" postQueryString="false"><con:settings><con:setting id="com.eviware.soapui.impl.wsdl.WsdlRequest@request-headers">&lt;entry key="Authorization" value="pk_2144423805_3GVK169890OTH81FLY3REPUZEXTG31S5" xmlns="http://eviware.com/soapui/config"/></con:setting></con:settings><con:endpoint>https://app.clickup.com</con:endpoint><con:request>{
    "tag": {
      "name": "new_123",
      "tag_fg": "#000000",
      "tag_bg": "#000000"
    }
  }</con:request><con:originalUri>https://app.clickup.com/</con:originalUri><con:credentials><con:authType>No Authorization</con:authType></con:credentials><con:jmsConfig JMSDeliveryMode="PERSISTENT"/><con:jmsPropertyConfig/><con:parameters/><con:parameterOrder/></con:request></con:method></con:resource><con:resource name="" path="/api/v2/task/869646rwu/tag/${#Project#tag_name}" id="f7e01f19-5f6a-4b29-a627-81c8c81fdec9"><con:settings/><con:parameters><con:parameter><con:name>tag_name</con:name><con:value>tag_name</con:value><con:style>TEMPLATE</con:style><con:default>tag_name</con:default></con:parameter></con:parameters><con:method name="ADD_TAG_TO_TASK" id="6aa0578f-8c84-4873-b567-2a5c4987a7de" method="POST"><con:settings/><con:parameters/><con:representation type="RESPONSE"><con:mediaType>text/html; charset=utf-8</con:mediaType><con:status>200</con:status><con:params/><con:element>html</con:element></con:representation><con:representation type="REQUEST"><con:mediaType>application/json</con:mediaType><con:params/></con:representation><con:representation type="RESPONSE"><con:mediaType>application/json; charset=utf-8</con:mediaType><con:status>200</con:status><con:params/><con:element>Response</con:element></con:representation><con:request name="add tag to task" id="c882f0a5-e5e4-402a-925c-f96b5727031a" mediaType="application/json" postQueryString="false"><con:settings><con:setting id="com.eviware.soapui.impl.wsdl.WsdlRequest@request-headers">&lt;entry key="Authorization" value="pk_2144423805_3GVK169890OTH81FLY3REPUZEXTG31S5" xmlns="http://eviware.com/soapui/config"/></con:setting></con:settings><con:endpoint>https://app.clickup.com</con:endpoint><con:request/><con:originalUri>https://app.clickup.com/api/v2/task/869646rwu/tag/</con:originalUri><con:credentials><con:authType>No Authorization</con:authType></con:credentials><con:jmsConfig JMSDeliveryMode="PERSISTENT"/><con:jmsPropertyConfig/><con:parameters/><con:parameterOrder><con:entry>tag_name</con:entry></con:parameterOrder></con:request></con:method><con:method name="REVOME_TAG_FROM_TASK" id="e3e38eed-ebbe-4935-b42f-de7be02ac5ec" method="DELETE"><con:settings/><con:parameters/><con:representation type="RESPONSE"><con:mediaType>application/json; charset=utf-8</con:mediaType><con:status>200</con:status><con:params/><con:element>Response</con:element></con:representation><con:representation type="REQUEST"><con:mediaType>application/json</con:mediaType><con:params/></con:representation><con:request name="remove tag from task" id="215a8670-22a6-4082-a037-2c973f978aeb" mediaType="application/json" postQueryString="false"><con:settings><con:setting id="com.eviware.soapui.impl.wsdl.WsdlRequest@request-headers">&lt;entry key="Authorization" value="pk_2144423805_3GVK169890OTH81FLY3REPUZEXTG31S5" xmlns="http://eviware.com/soapui/config"/></con:setting></con:settings><con:endpoint>https://app.clickup.com</con:endpoint><con:request/><con:originalUri>https://app.clickup.com/api/v2/task/869646rwu/tag/new_tag_name</con:originalUri><con:credentials><con:authType>No Authorization</con:authType></con:credentials><con:jmsConfig JMSDeliveryMode="PERSISTENT"/><con:jmsPropertyConfig/><con:parameters/><con:parameterOrder><con:entry>tag_name</con:entry></con:parameterOrder></con:request></con:method></con:resource><con:resource name="" path="/api/v2/space/90121507775/tag/new_123" id="9cb6d019-5c39-428d-8c15-624bbca161a5"><con:settings/><con:parameters/><con:method name="DELETE_SPACE_TAG" id="54872ace-0d2d-4502-8ad9-d334d29f25e4" method="DELETE"><con:settings/><con:parameters/><con:representation type="FAULT"><con:mediaType>application/json; charset=utf-8</con:mediaType><con:status>400</con:status><con:params/><con:element xmlns:new="https://app.clickup.com/api/v2/space/90121507775/tag/new_123">new:Fault</con:element></con:representation><con:representation type="REQUEST"><con:mediaType>application/json</con:mediaType><con:params/></con:representation><con:representation type="RESPONSE"><con:mediaType>application/json; charset=utf-8</con:mediaType><con:status>200</con:status><con:params/><con:element>Response</con:element></con:representation><con:request name="delete space tag" id="1b9818d3-5c1d-4588-a7ac-8afbe1ec053e" mediaType="application/json" postQueryString="false"><con:settings><con:setting id="com.eviware.soapui.impl.wsdl.WsdlRequest@request-headers">&lt;entry key="Authorization" value="pk_2144423805_3GVK169890OTH81FLY3REPUZEXTG31S5" xmlns="http://eviware.com/soapui/config"/></con:setting></con:settings><con:endpoint>https://app.clickup.com</con:endpoint><con:request/><con:originalUri>https://app.clickup.com/api/v2/space/90121507775/tag/new_123</con:originalUri><con:credentials><con:authType>No Authorization</con:authType></con:credentials><con:jmsConfig JMSDeliveryMode="PERSISTENT"/><con:jmsPropertyConfig/><con:parameters/></con:request></con:method></con:resource></con:interface><con:testSuite id="b12337a5-332f-4e77-a8c1-d943202fb560" name="CRUD test"><con:description>TestSuite generated for REST Service [https://api.clickup.com]</con:description><con:settings/><con:runType>SEQUENTIAL</con:runType><con:testCase id="e0ef30f8-3175-40b0-8475-70060e8a9155" failOnError="true" failTestCaseOnErrors="true" keepSession="false" maxResults="0" name="TestCase" searchProperties="true"><con:description>TestCase generated for REST Resource [] located at [/api/v2/space/90121507775/tag]</con:description><con:settings/><con:testStep type="groovy" name="random_name" id="cbce6266-b814-4ac2-9097-aa4695c2f608"><con:settings/><con:config><script>// Генерируем рандомное число от 1 до 1000
def randomNumber = new Random().nextInt(1000) + 1

// Формируем рандомное имя переменной
def randomName = "random_name_" + randomNumber

// Сохраняем имя переменной в свойство на уровне проекта
context.testCase.testSuite.project.setPropertyValue("random_name", randomName)

// Выводим результат в лог для проверки
log.info("Сгенерированное имя переменной сохранено на уровне проекта: " + randomName)</script></con:config></con:testStep><con:testStep type="restrequest" name="create space tag" id="348a4ade-2ecc-4bb3-b7d6-dc52ff453cf6"><con:settings/><con:config service="https://api.clickup.com" resourcePath="/api/v2/space/90121507775/tag" methodName="CREATE_SPACE_TAG" xsi:type="con:RestRequestStep" xmlns:xsi="http://www.w3.org/2001/XMLSchema-instance"><con:restRequest name="create space tag" id="a67613de-d7ae-4355-92c1-9f1bc1939f2b" mediaType="application/json" postQueryString="false"><con:settings><con:setting id="com.eviware.soapui.impl.wsdl.WsdlRequest@request-headers">&lt;entry key="Authorization" value="pk_2144423805_3GVK169890OTH81FLY3REPUZEXTG31S5" xmlns="http://eviware.com/soapui/config"/></con:setting></con:settings><con:endpoint>https://api.clickup.com</con:endpoint><con:request>{ 
  "tag": {
    "name": "${#Project#random_name}",
    "tag_fg": "#000000",
    "tag_bg": "#000000"
  }
}
</con:request><con:originalUri>https://app.clickup.com/api/v2/space/90121507775/tag</con:originalUri><con:assertion type="Valid HTTP Status Codes" id="94404118-f30d-47f2-9c7f-38e092c3d94f" name="Valid HTTP Status Codes"><con:configuration><codes>200</codes></con:configuration></con:assertion><con:credentials><con:selectedAuthProfile>No Authorization</con:selectedAuthProfile><con:authType>No Authorization</con:authType></con:credentials><con:jmsConfig JMSDeliveryMode="PERSISTENT"/><con:jmsPropertyConfig/><con:parameters/></con:restRequest></con:config></con:testStep><con:testStep type="restrequest" name="get space tags" id="27267df5-8e28-4bb5-af48-35362c3d290a"><con:settings/><con:config service="https://api.clickup.com" resourcePath="/api/v2/space/90121507775/tag" methodName="GET_SPACE_TAGS" xsi:type="con:RestRequestStep" xmlns:xsi="http://www.w3.org/2001/XMLSchema-instance"><con:restRequest name="get space tags" id="ece4374c-4a11-41e1-b4cb-b367d7f4af83" mediaType="application/json"><con:settings><con:setting id="com.eviware.soapui.impl.wsdl.WsdlRequest@request-headers">&lt;entry key="Authorization" value="pk_2144423805_3GVK169890OTH81FLY3REPUZEXTG31S5" xmlns="http://eviware.com/soapui/config"/></con:setting></con:settings><con:endpoint>https://api.clickup.com</con:endpoint><con:request/><con:originalUri>https://app.clickup.com/api/v2/space/90121507775/tag</con:originalUri><con:assertion type="Valid HTTP Status Codes" id="e891e77b-ef8a-4306-8181-736ec9781a42" name="Valid HTTP Status Codes"><con:configuration><codes>200</codes></con:configuration></con:assertion><con:credentials><con:authType>No Authorization</con:authType></con:credentials><con:jmsConfig JMSDeliveryMode="PERSISTENT"/><con:jmsPropertyConfig/><con:parameters/></con:restRequest></con:config></con:testStep><con:testStep type="restrequest" name="edit space tag" id="3bf4242a-da86-4f3e-9ed3-31dcdb1e2de9"><con:settings/><con:config service="https://api.clickup.com" resourcePath="/api/v2/space/90121507775/tag/${#Project#random_name}" methodName="EDIT_SPACE_TAG" xsi:type="con:RestRequestStep" xmlns:xsi="http://www.w3.org/2001/XMLSchema-instance"><con:restRequest name="edit space tag" id="514cd945-461d-4f7d-bc69-74aff4a9023b" mediaType="application/json" postQueryString="false"><con:settings><con:setting id="com.eviware.soapui.impl.wsdl.WsdlRequest@request-headers">&lt;entry key="Authorization" value="pk_2144423805_3GVK169890OTH81FLY3REPUZEXTG31S5" xmlns="http://eviware.com/soapui/config"/></con:setting></con:settings><con:endpoint>https://app.clickup.com</con:endpoint><con:request>{
    "tag": {
      "name": "new_123",
      "tag_fg": "#000000",
      "tag_bg": "#000000"
    }
  }</con:request><con:originalUri>https://app.clickup.com/</con:originalUri><con:assertion type="Valid HTTP Status Codes" id="d7b623d7-ee92-4f2b-a0eb-94f798c872fe" name="Valid HTTP Status Codes"><con:configuration><codes>200</codes></con:configuration></con:assertion><con:credentials><con:authType>No Authorization</con:authType></con:credentials><con:jmsConfig JMSDeliveryMode="PERSISTENT"/><con:jmsPropertyConfig/><con:parameters/><con:parameterOrder/></con:restRequest></con:config></con:testStep><con:testStep type="restrequest" name="add tag to task" id="60ccbf49-4a5b-423b-bb64-8263a8a7b22a"><con:settings/><con:config service="https://api.clickup.com" resourcePath="/api/v2/task/869646rwu/tag/${#Project#tag_name}" methodName="ADD_TAG_TO_TASK" xsi:type="con:RestRequestStep" xmlns:xsi="http://www.w3.org/2001/XMLSchema-instance"><con:restRequest name="add tag to task" id="c882f0a5-e5e4-402a-925c-f96b5727031a" mediaType="application/json" postQueryString="false"><con:settings><con:setting id="com.eviware.soapui.impl.wsdl.WsdlRequest@request-headers">&lt;entry key="Authorization" value="pk_2144423805_3GVK169890OTH81FLY3REPUZEXTG31S5" xmlns="http://eviware.com/soapui/config"/></con:setting></con:settings><con:endpoint>https://app.clickup.com</con:endpoint><con:request/><con:originalUri>https://app.clickup.com/api/v2/task/869646rwu/tag/</con:originalUri><con:assertion type="Valid HTTP Status Codes" id="681dba69-3e07-48e8-844d-3f75e31e2183" name="Valid HTTP Status Codes"><con:configuration><codes>200</codes></con:configuration></con:assertion><con:credentials><con:authType>No Authorization</con:authType></con:credentials><con:jmsConfig JMSDeliveryMode="PERSISTENT"/><con:jmsPropertyConfig/><con:parameters/><con:parameterOrder><con:entry>tag_name</con:entry></con:parameterOrder></con:restRequest></con:config></con:testStep><con:testStep type="restrequest" name="remove tag from task" id="83d0f408-9d8e-422f-aede-60a2f1bafc50"><con:settings/><con:config service="https://api.clickup.com" resourcePath="/api/v2/task/869646rwu/tag/${#Project#tag_name}" methodName="REVOME_TAG_FROM_TASK" xsi:type="con:RestRequestStep" xmlns:xsi="http://www.w3.org/2001/XMLSchema-instance"><con:restRequest name="remove tag from task" id="215a8670-22a6-4082-a037-2c973f978aeb" mediaType="application/json" postQueryString="false"><con:settings><con:setting id="com.eviware.soapui.impl.wsdl.WsdlRequest@request-headers">&lt;entry key="Authorization" value="pk_2144423805_3GVK169890OTH81FLY3REPUZEXTG31S5" xmlns="http://eviware.com/soapui/config"/></con:setting></con:settings><con:endpoint>https://app.clickup.com</con:endpoint><con:request/><con:originalUri>https://app.clickup.com/api/v2/task/869646rwu/tag/</con:originalUri><con:assertion type="Valid HTTP Status Codes" id="ddee4a36-4c92-47d2-8549-880bbf8fbe21" name="Valid HTTP Status Codes"><con:configuration><codes>200</codes></con:configuration></con:assertion><con:credentials><con:authType>No Authorization</con:authType></con:credentials><con:jmsConfig JMSDeliveryMode="PERSISTENT"/><con:jmsPropertyConfig/><con:parameters/><con:parameterOrder><con:entry>tag_name</con:entry></con:parameterOrder></con:restRequest></con:config></con:testStep><con:testStep type="restrequest" name="delete space tag" id="cc7a9bd8-c690-4d28-a4ed-e0a7b6efac5d"><con:settings/><con:config service="https://api.clickup.com" resourcePath="/api/v2/space/90121507775/tag/new_123" methodName="DELETE_SPACE_TAG" xsi:type="con:RestRequestStep" xmlns:xsi="http://www.w3.org/2001/XMLSchema-instance"><con:restRequest name="delete space tag" id="1b9818d3-5c1d-4588-a7ac-8afbe1ec053e" mediaType="application/json" postQueryString="false"><con:settings><con:setting id="com.eviware.soapui.impl.wsdl.WsdlRequest@request-headers">&lt;entry key="Authorization" value="pk_2144423805_3GVK169890OTH81FLY3REPUZEXTG31S5" xmlns="http://eviware.com/soapui/config"/></con:setting></con:settings><con:endpoint>https://app.clickup.com</con:endpoint><con:request/><con:originalUri>https://app.clickup.com/api/v2/space/90121507775/tag/new_123</con:originalUri><con:assertion type="Valid HTTP Status Codes" id="1bb7c717-7d19-457a-9ba1-fd008285f85d" name="Valid HTTP Status Codes"><con:configuration><codes>200</codes></con:configuration></con:assertion><con:credentials><con:authType>No Authorization</con:authType></con:credentials><con:jmsConfig JMSDeliveryMode="PERSISTENT"/><con:jmsPropertyConfig/><con:parameters/></con:restRequest></con:config></con:testStep><con:properties/></con:testCase><con:properties/></con:testSuite><con:properties><con:property><con:name>random_name</con:name><con:value>random_name_348</con:value></con:property><con:property><con:name>tag_name</con:name><con:value>new_tag_name</con:value></con:property></con:properties><con:wssContainer/><con:oAuth2ProfileContainer/><con:oAuth1ProfileContainer/><con:sensitiveInformation/></con:soapui-project>